explainthis/ExplainThis.py
explainthis/__init__.py
explainthis/errors.json
explainthis/errors.py
explainthis/themes.json
explainthis/utils.py
explainthis-0.2.1.dist-info/LICENSE
explainthis-0.2.1.dist-info/METADATA
explainthis-0.2.1.dist-info/WHEEL
explainthis-0.2.1.dist-info/top_level.txt
explainthis-0.2.1.dist-info/RECORD
