Metadata-Version: 2.1
Name: explainthis
Version: 0.2.1
Summary: Beginner-friendly error tracing for Python.
Home-page: https://github.com/00-Masterpiece/ExplainThis
Author: Jaden Gregory
Author-email: jaden.andru@gmail.com
License: Proprietary
Classifier: Programming Language :: Python :: 3
Classifier: Operating System :: OS Independent
Classifier: License :: Other/Proprietary License
Requires-Python: >=3.7
License-File: LICENSE
Requires-Dist: rich >=13.0
